MANIFEST.in
README.rst
setup.cfg
setup.py
strapmin/__init__.py
strapmin/widgets.py
strapmin.egg-info/PKG-INFO
strapmin.egg-info/SOURCES.txt
strapmin.egg-info/dependency_links.txt
strapmin.egg-info/requires.txt
strapmin.egg-info/top_level.txt
strapmin/static/admin/css/base.css
strapmin/static/admin/css/base.less
strapmin/static/admin/css/bootstrap.min.css
strapmin/static/admin/fonts/glyphicons-halflings-regular.eot
strapmin/static/admin/fonts/glyphicons-halflings-regular.svg
strapmin/static/admin/fonts/glyphicons-halflings-regular.ttf
strapmin/static/admin/fonts/glyphicons-halflings-regular.woff
strapmin/static/admin/js/SelectFilter2.js
strapmin/static/admin/js/bootstrap.min.js
strapmin/static/admin/js/ckeditor/CHANGES.md
strapmin/static/admin/js/ckeditor/LICENSE.md
strapmin/static/admin/js/ckeditor/README.md
strapmin/static/admin/js/ckeditor/build-config.js
strapmin/static/admin/js/ckeditor/ckeditor.js
strapmin/static/admin/js/ckeditor/config.js
strapmin/static/admin/js/ckeditor/contents.css
strapmin/static/admin/js/ckeditor/jquery-ckeditor.js
strapmin/static/admin/js/ckeditor/styles.js
strapmin/static/admin/js/ckeditor/adapters/jquery.js
strapmin/static/admin/js/ckeditor/lang/af.js
strapmin/static/admin/js/ckeditor/lang/ar.js
strapmin/static/admin/js/ckeditor/lang/bg.js
strapmin/static/admin/js/ckeditor/lang/bn.js
strapmin/static/admin/js/ckeditor/lang/bs.js
strapmin/static/admin/js/ckeditor/lang/ca.js
strapmin/static/admin/js/ckeditor/lang/cs.js
strapmin/static/admin/js/ckeditor/lang/cy.js
strapmin/static/admin/js/ckeditor/lang/da.js
strapmin/static/admin/js/ckeditor/lang/de.js
strapmin/static/admin/js/ckeditor/lang/el.js
strapmin/static/admin/js/ckeditor/lang/en-au.js
strapmin/static/admin/js/ckeditor/lang/en-ca.js
strapmin/static/admin/js/ckeditor/lang/en-gb.js
strapmin/static/admin/js/ckeditor/lang/en.js
strapmin/static/admin/js/ckeditor/lang/eo.js
strapmin/static/admin/js/ckeditor/lang/es.js
strapmin/static/admin/js/ckeditor/lang/et.js
strapmin/static/admin/js/ckeditor/lang/eu.js
strapmin/static/admin/js/ckeditor/lang/fa.js
strapmin/static/admin/js/ckeditor/lang/fi.js
strapmin/static/admin/js/ckeditor/lang/fo.js
