Metadata-Version: 1.1
Name: strapmin
Version: 0.5.9
Summary: A bootstrappy django admin reskin
Home-page: UNKNOWN
Author: Tom Carrick
Author-email: knyght@knyg.ht
License: BSD 2 Clause
Platform: UNKNOWN
Requires: django (>= 1.5)
